flwr_monitoring/__init__.py
flwr_monitoring/aggregate_functions.py
flwr_monitoring/base_monitoring_strategy.py
flwr_monitoring/base_monitoring_tool.py
flwr_monitoring/config.py
flwr_monitoring/custom_fedavg_strategy.py
flwr_monitoring/generic_monitoring_strategy.py
flwr_monitoring/metrics.py
flwr_monitoring/monitoring_factory.py
flwr_monitoring/monitoring_strategy.py
flwr_monitoring/prometheus_monitoring.py
flwr_monitoring/wandb_monitoring.py
flwr_monitoring-0.2.0.dist-info/METADATA
flwr_monitoring-0.2.0.dist-info/WHEEL
flwr_monitoring-0.2.0.dist-info/top_level.txt
flwr_monitoring-0.2.0.dist-info/RECORD
