Metadata-Version: 2.1
Name: flwr_monitoring
Version: 0.2.0
Summary: A package for monitoring Flower federated learning framework using Prometheus and WandB
Home-page: https://github.com/kandola-network/KanFL
Author: Kandola
Author-email: Vishal Gupta <vishalsg42+pip@gmail.com>
Maintainer-email: Vishal Gupta <vishalsg42+pip@gmail.com>
License: MIT
Project-URL: Homepage, https://github.com/kandola-network/KanFL
Keywords: flower,monitoring,federated learning,prometheus,wandb
Classifier: Programming Language :: Python :: 3
Requires-Python: >=3.7
Requires-Dist: flwr ==1.11.0
Requires-Dist: GPUtil ==1.4.0
Requires-Dist: psutil ==6.0.0
Requires-Dist: prometheus-client ==0.20.0
Requires-Dist: wandb ==0.17.7
